README.rst
setup.cfg
setup.py
peek_desktop/__init__.py
peek_desktop/tslint.json
peek_desktop.egg-info/PKG-INFO
peek_desktop.egg-info/SOURCES.txt
peek_desktop.egg-info/dependency_links.txt
peek_desktop.egg-info/not-zip-safe
peek_desktop.egg-info/top_level.txt
peek_desktop/build-web/README.md
peek_desktop/build-web/angular.json
peek_desktop/build-web/browserslist
peek_desktop/build-web/karma.conf.js
peek_desktop/build-web/package-lock.json
peek_desktop/build-web/package.json
peek_desktop/build-web/protractor.conf.js
peek_desktop/build-web/proxy.conf.json
peek_desktop/build-web/tsconfig.json
peek_desktop/build-web/tslint.json
peek_desktop/build-web/e2e/app.e2e-spec.ts
peek_desktop/build-web/e2e/app.po.ts
peek_desktop/build-web/e2e/tsconfig.e2e.json
peek_desktop/build-web/src/app.web.module.ts
peek_desktop/build-web/src/favicon.ico
peek_desktop/build-web/src/index.html
peek_desktop/build-web/src/main.ts
peek_desktop/build-web/src/polyfills.ts
peek_desktop/build-web/src/styles.scss
peek_desktop/build-web/src/test.ts
peek_desktop/build-web/src/tsconfig.app.json
peek_desktop/build-web/src/tsconfig.spec.json
peek_desktop/build-web/src/typings.d.ts
peek_desktop/build-web/src/assets/home-background.png
peek_desktop/build-web/src/assets/home-center.png
peek_desktop/build-web/src/assets/sidebar_background.png
peek_desktop/build-web/src/environments/environment.prod.ts
peek_desktop/build-web/src/environments/environment.ts
peek_desktop/src/app/app.component.dweb.html
peek_desktop/src/app/app.component.dweb.scss
peek_desktop/src/app/app.component.ts
peek_desktop/src/app/app.routes.ts
peek_desktop/src/app/app.services.ts
peek_desktop/src/app/plugin-root.component.ts
peek_desktop/src/app/main-config/main-config.component.dweb.html
peek_desktop/src/app/main-config/main-config.component.ts
peek_desktop/src/app/main-home/main-home.component.dweb.html
peek_desktop/src/app/main-home/main-home.component.dweb.scss
peek_desktop/src/app/main-home/main-home.component.ts
peek_desktop/src/app/main-sidebar/main-sidebar.component.dweb.html
peek_desktop/src/app/main-sidebar/main-sidebar.component.dweb.scss
peek_desktop/src/app/main-sidebar/main-sidebar.component.ts
