Metadata-Version: 1.1
Name: peek-desktop
Version: 2.5.2
Summary: Peek Platform - desktop Service (Frontend)
Home-page: https://github.com/Synerty/peek-desktop
Author: Synerty
Author-email: contact@synerty.com
License: UNKNOWN
Download-URL: https://github.com/Synerty/peek-desktop/tarball/2.5.2
Keywords: Peek,Python,Platform,synerty
Platform: UNKNOWN
Classifier: Programming Language :: Python :: 3.6
